imcntr/__init__.py
imcntr/communication_handler.py
imcntr/communication_protocol.py
imcntr/controller_api.py
imcntr/observer.py
imcntr-2.0.0.dist-info/LICENSE
imcntr-2.0.0.dist-info/METADATA
imcntr-2.0.0.dist-info/WHEEL
imcntr-2.0.0.dist-info/RECORD
