Metadata-Version: 2.3
Name: imcntr
Version: 2.0.0
Summary: A package providing an API for imaging controller based on an Arduino Nano Every to communicate via serial port.
License: MIT
Author: Clemens Trunner
Requires-Python: >=3.9
Classifier: License :: OSI Approved :: MIT License
Classifier: Programming Language :: Python :: 3
Classifier: Programming Language :: Python :: 3.9
Classifier: Programming Language :: Python :: 3.10
Classifier: Programming Language :: Python :: 3.11
Classifier: Programming Language :: Python :: 3.12
Classifier: Programming Language :: Python :: 3.13
Requires-Dist: pyserial (>=3.5)
